<?xml version="1.0" encoding="windows-1252"?>
<node id="357799" title="section list" created="2004-05-31 10:56:42" updated="2005-04-20 10:28:00">
<type id="871">
setting</type>
<author id="321667">
theonetwo</author>
<vars count="20">
<var name="CUFP">
Cool Uses for Perl</var>
<var name="bookreview">
Book Reviews</var>
<var name="categorized_answer">
Categorized Questions and Answers</var>
<var name="categorized_question">
Categorized Questions and Answers</var>
<var name="modulereview">
Module Reviews</var>
<var name="monkdiscuss">
Perl Monks Discussion</var>
<var name="obfuscated">
Obfuscated Code</var>
<var name="perlcraft">
Craft</var>
<var name="perlmeditation">
Meditations</var>
<var name="perlnews">
Perl News</var>
<var name="perlquestion">
Seekers of Perl Wisdom</var>
<var name="perltutorial">
Tutorials</var>
<var name="pmdevtopic">
Inner Scriptorium</var>
<var name="poem">
Perl Poetry</var>
<var name="poll">
Past Polls</var>
<var name="quest">
Quests</var>
<var name="request">
Editor Requests</var>
<var name="sitefaqlet">
PerlMonks FAQ</var>
<var name="snippet">
Snippets Section</var>
<var name="sourcecode">
Code Catacombs</var>
</vars>
</node>
