<node>
  <parent_container>1058</parent_container>
  <type_nodetype>9</type_nodetype>
  <author_user>929</author_user>
  <createtime>2002-04-27 02:08:52</createtime>
  <node_id>162477</node_id>
  <title>Monthly Best</title>
  <nlcode>[%
  # add user setting for number of nodes to return
  htmlcode('get_picked_nodes','',
            time_text =&gt; &quot;The Month&quot;,
            type   =&gt; &quot;Best&quot;, 
            order  =&gt; &quot;DESC&quot;,
            days   =&gt; 30,
            choose =&gt; 10,
            max_age=&gt; 0,
            style  =&gt; 'nodelet'
          )
%]
</nlcode>
  <nodeupdated>1331214098</nodeupdated>
</node>
