<?xml version="1.0" encoding="windows-1252"?>
<node id="487572" title="How does editing work in the Tutorials section?" created="2005-08-29 17:59:22" updated="2005-08-29 13:59:22">
<type id="17338">
sitefaqlet</type>
<author id="17342">
SiteDocClan</author>
<data>
<field name="doctext">
&lt;!-- 2005-08-29 [jdporter] created --&gt;

&lt;h1&gt;How does editing work in the [id://954] section?&lt;/h1&gt;

&lt;p&gt;
Whenever someone creates a Tutorial-type writeup (using the form at the bottom of the [id://954] page), it automatically appears in the 
[id://519201] category of [id://954].
&lt;/p&gt;&lt;p&gt;
The only thing remaining is to give it a permanent home in an appropriate category. The people with this ability are the [Pedagogues].
Therefore, if it seems like they're taking their sweet time pidgeonholing a tutorial, feel free to tickle them via &lt;tt&gt;[msg://Pedagogues]&lt;/tt&gt;.
If possible, please include the name of the existing [Tutorials] category in which you believe the given tutorial would be most appropriate.
&lt;/p&gt;

&lt;p&gt;
Note: [Pedagogues] do not have the power to modify tutorial posts in any way. For that, all the standard [id://17688|moderation] and [id://92975|consideration] procedures apply.
&lt;/p&gt;

&lt;hr/&gt;

&lt;h3&gt;If you're a [Pedagogues|Pedagogue]:&lt;/h3&gt;

&lt;p&gt;
&lt;ol&gt;
&lt;li&gt; Go to the [id://954] page. You should see the new tutorial listed in the [id://519201] section. &lt;/li&gt;
&lt;li&gt; Click the header of the section into which
the new tutorial is to be added.
(For example, &lt;b&gt;[id://519264]&lt;/b&gt;.) &lt;/li&gt;
&lt;li&gt; Click the "Edit" link in the upper right. &lt;/li&gt;
&lt;li&gt; Type/paste the node id &amp;mdash; &lt;b&gt;just the ID&lt;/b&gt; &amp;mdash; into the next available slot in the list, and click the "submit below" button. &lt;/li&gt;
&lt;/ol&gt;
See [id://587754] for more details.
&lt;/p&gt;

&lt;hr/&gt;&lt;i&gt;Return to [PerlMonks FAQ]&lt;/i&gt;
</field>
</data>
</node>
