<?xml version="1.0" encoding="windows-1252"?>
<node id="726673" title="How do I log out?" created="2008-11-28 16:25:20" updated="2008-11-28 16:25:20">
<type id="17338">
sitefaqlet</type>
<author id="17342">
SiteDocClan</author>
<data>
<field name="doctext">
&lt;h1&gt;How do I log out?&lt;/h1&gt;
&lt;p&gt;
Assuming you have not disabled the navigation menu under the title bar via your [User Settings], the very first link in the list will say "Log &lt;i&gt;Myself&lt;/i&gt; out". Click that to log out.
&lt;/p&gt;
&lt;p&gt;
Similarly, if you have the [About the Leftovers Nodelet|Leftovers Nodelet] enabled via your [id://25185], the link is there.
&lt;/p&gt;
&lt;p&gt;
If you're reading this node and you want to log out &lt;i&gt;now&lt;/i&gt;, then here's the link for you convenience:
[href://?op=logout|Log out now].
&lt;/p&gt;
&lt;p&gt;
Of course, none of this makes sense unless you are [id://156909|logged in].
&lt;/p&gt;
</field>
</data>
</node>
