<?xml version="1.0" encoding="windows-1252"?>
<node id="43196" title="Best part of Thanksgiving" created="2000-11-24 04:37:17" updated="2005-08-14 14:15:32">
<type id="1440">
poll</type>
<author id="979">
vroom</author>
<data>
<field name="choices">
Turkey and good food
Good nontraditional meal (no turkey involved)
Football
The holiday weight gain... now people won't be able to call me a 90lb (40.8 kg) weakling
Seeing family
The trip to Express Island Convenience Store or equivalent after the family get together
The fact that I'm not an American and don't celebrate that bloody holiday</field>
<field name="numbers">
92
19
15
8
34
5
107</field>
</data>
</node>
