<?xml version="1.0" encoding="windows-1252"?>
<node id="486258" title="I'm *going* to [http://braga.yapceurope.org/|YAPC Europe: Braga, Portugal], because" created="2005-08-24 11:57:38" updated="2005-08-24 07:57:38">
<type id="1440">
poll</type>
<author id="326280">
cog</author>
<data>
<field name="choices">
I don't know what else to do with my money
I like good food
I like good desserts
I like the idea of three days of Perl
They're forcing me to go
I like good weather
I like cheap beer
I want to meet all you guys
What do you mean, going?
I want to see what happens to those who voted for [http://braga.yapceurope.org/index.cgi?TheFishnetsIncident|fishnets]</field>
<field name="numbers">
3
1
1
8
2
2
11
5
128
33</field>
</data>
</node>
