<?xml version="1.0" encoding="windows-1252"?>
<node id="726816" title="I work..." created="2008-11-29 13:49:55" updated="2008-11-29 13:49:55">
<type id="1440">
poll</type>
<author id="603247">
apl</author>
<data>
<field name="choices">
at home
from the nearest Starbucks
in an office
in a cubicle farm
shoulder to shoulder with my team-mates
wherever there's a free Wifi connection
all of the above
Work? What is this work?
Other
</field>
<field name="numbers">
100
3
165
86
27
8
63
68
23</field>
</data>
</node>
