<?xml version="1.0" encoding="windows-1252"?>
<node id="1308" title="perlman:Thread::index" created="1999-12-22 21:30:10" updated="2005-06-13 12:19:14">
<type id="116">
perlman</type>
<author id="113">
root</author>
<data>
<field name="doctext">
&lt;TITLE&gt;Contents of Thread&lt;/TITLE&gt;
&lt;H1&gt;Contents of Thread&lt;/H1&gt;
&lt;DL&gt;
&lt;DT&gt;&lt;A HREF="../../READMEs/README.threads"&gt;README&lt;/A&gt;&lt;DD&gt;How to build a
threaded Perl.
&lt;DT&gt;[perlman:lib:Thread|Thread]&lt;DD&gt;multithreading
&lt;DT&gt;[perlman:Thread::Queue|Queue]&lt;DD&gt;thread-safe queues
&lt;DT&gt;[perlman:Thread::Semaphore|Semaphore]&lt;DD&gt;thread-safe semaphores
&lt;DT&gt;[perlman:Thread::Signal|Signal]&lt;DD&gt;Start a thread which runs signal handlers reliably
&lt;DT&gt;[perlman:Thread::Specific|Specific]&lt;DD&gt;thread-specific keys
&lt;/DL&gt;
</field>
</data>
</node>
