<node>
  <type_nodetype>1440</type_nodetype>
  <node_id>383208</node_id>
  <numbers>75
69
45
119
193
70
4
28
10
15
51
42</numbers>
  <author_user>142755</author_user>
  <title>At my main job I mostly occupy my...</title>
  <createtime>2004-08-16 02:34:24</createtime>
  <choices>Home
Office with a window
Private office
Shared office
Cubicle
Desk
Vehicle
Place to sit
Place to stand
None of the above
I'd like a job
Jobs are for poor people</choices>
  <nodeupdated>2005-08-12 19:31:18</nodeupdated>
</node>
