<node>
  <type_nodetype>1440</type_nodetype>
  <node_id>578680</node_id>
  <numbers>11
8
1
15
31
30
26
30
30
74
79</numbers>
  <author_user>29008</author_user>
  <title>If I was forced to program in another language, the Perl language feature I would miss most would be:</title>
  <createtime>2006-10-17 02:32:23</createtime>
  <choices>formats
heredocs
do blocks
block eval
array slices
qw operator
next and last
trailing commas
statement modifiers
variable interpolation
anonymous subroutines</choices>
  <nodeupdated>2006-10-16 22:32:23</nodeupdated>
</node>
