<node>
  <type_nodetype>1440</type_nodetype>
  <node_id>585010</node_id>
  <numbers>16
6
22
5
19
21
7
51
21
22
1
5
7
8
12
11
3
9
3
11
12
34
7
3
16
40</numbers>
  <author_user>442602</author_user>
  <title>In &quot;PerlMonks: The Motion Picture,&quot; the Vote Fairy would best be portrayed by...</title>
  <createtime>2006-11-20 00:06:30</createtime>
  <choices>[imdb://Jodie Foster] .... [imdb://The Little Girl Who Lives Down the Lane|Rynn]
[imdb://Kate O'Mara] .... [imdb://Doctor Who Time and the Rani|The Rani]
[imdb://Jennifer Aniston] .... [imdb://Office Space|Joanna]
[imdb://Jodie Foster] .... [imdb://Taxi Driver|Iris Steensma]
[imdb://Tilda Swinton] .... [imdb://The Chronicles of Narnia|White Witch]
[imdb://Alice Krige] .... [imdb://Star Trek Voyager|The Borg Queen]
[imdb://Hilary Swank] .... [imdb://Boys Don't Cry|Brandon Teena]
[imdb://Christina Ricci] .... [imdb://The Addams Family|Wednesday Addams]
[imdb://Helena Bonham Carter] .... [imdb://Corpse Bride|Corpse Bride]
[imdb://Kirsten Dunst] .... [imdb://Interview with the Vampire|Claudia, the child vampire]
[imdb://Ingrid Pitt] .... [imdb://The Vampire Lovers|Marcilla/Carmilla/Mircalla Karnstein]
[imdb://Terence Stamp] .... [imdb://The Adventures of Priscilla, Queen of the Desert|Ralph/Bernadette Bassenger]
[imdb://Arnold Schwarzenegger] .... [imdb://The Terminator]
[imdb://Max Von Sydow] .... [imdb://Flash Gordon|The Emperor Ming]
[imdb://Arnold Schwarzenegger] .... [wp://Arnold Schwarzenegger|Himself]
[imdb://Pee-wee Herman] .... [imdb://Pee-wee's Playhouse|Billy Baloney]
[imdb://Nathan Lane] .... [imdb://The Birdcage|Albert Goldman]
[imdb://Boris Karloff] .... [imdb://Frankenstein|The Monster]
[imdb://Paul Reiser] .... [imdb://Aliens|Carter Burke]
[imdb://Antonio Banderas] .... [imdb://The Mask of Zorro|Zorro]
[imdb://Rutger Hauer] .... [imdb://Blade Runner|Roy Batty]
[imdb://Ned Flanders] .... [wp://Ned Flanders|Himself]
[imdb://Brad Pitt] .... [imdb://Meet Joe Black|Joe Black]
[wp://Animatronic]
[wp://Claymation]
[wp://Computer-generated imagery|CGI]</choices>
  <nodeupdated>2006-11-19 19:06:30</nodeupdated>
</node>
