<?xml version="1.0" encoding="windows-1252"?>
<node id="14553" title="hint" created="2000-05-24 14:02:27" updated="2004-05-30 09:49:17">
<type id="1">
nodetype</type>
<author id="113">
root</author>
<data>
<field name="readers_user">
0</field>
<field name="writers_users">
</field>
<field name="deleters_users">
</field>
<field name="restrict_nodetype">
0</field>
<field name="extends_nodetype">
3</field>
<field name="restrictdupes">
0</field>
<field name="sqltable">
hint</field>
<field name="grouptable">
</field>
<field name="updaters_user">
0</field>
</data>
</node>
