<?xml version="1.0" encoding="windows-1252"?>
<node id="21149" title="review" created="2000-07-05 15:45:23" updated="2004-10-02 04:16:41">
<type id="1">
nodetype</type>
<author id="979">
vroom</author>
<data>
<field name="readers_user">
0</field>
<field name="writers_users">
</field>
<field name="deleters_users">
</field>
<field name="restrict_nodetype">
0</field>
<field name="extends_nodetype">
3</field>
<field name="restrictdupes">
0</field>
<field name="sqltable">
review</field>
<field name="grouptable">
</field>
<field name="updaters_user">
0</field>
</data>
</node>
