<?xml version="1.0" encoding="windows-1252"?>
<node id="511037" title="Reaped: Test adding tutorial" created="2005-11-23 04:45:18" updated="2005-11-22 23:47:35">
<type id="956">
perltutorial</type>
<author id="52855">
NodeReaper</author>
<data>
<field name="doctext">
This node was taken out by the [NodeReaper] on [localtime://2005-11-23 05-14-29]&lt;BR&gt;Reason:  &amp;#91;[davorg]]: delete&lt;p&gt;You may view [href://?node=Visit%20Reaped%20Nodes&amp;nodenum=511037|the original node and the consideration vote tally].&lt;/p&gt;</field>
</data>
</node>
