<node>
  <doctext>&lt;h1&gt;Is there PerlMonks merchandise I can buy?&lt;/h1&gt;
&lt;p&gt;
&lt;b&gt;Yes!  Visit the 
&lt;a href=&quot;http://www.cafepress.com/perlmonks&quot;&gt;PerlMonks CafePress Store&lt;/a&gt;!&lt;/b&gt;
&lt;/p&gt;
&lt;p&gt;
&lt;a href=&quot;http://shop.cafepress.com/perlmonks&quot;&gt;
&lt;img src=&quot;images/cafepress.gif&quot; border=&quot;0&quot; alt=&quot;sample merchandise&quot; /&gt;&lt;/a&gt;
&lt;/p&gt;
&lt;p&gt;
&lt;i&gt;&lt;b&gt;Note&lt;/b&gt;: If you find any problems with the info/links on this page,
please [msg://SiteDocClan|notify SiteDocClan]. Thanks!&lt;/i&gt;
&lt;/p&gt;
&lt;hr/&gt;&lt;i&gt;Back to the [PerlMonks FAQ]&lt;/i&gt;
</doctext>
  <type_nodetype>17338</type_nodetype>
  <node_id>781756</node_id>
  <author_user>17342</author_user>
  <title>Is there PerlMonks merchandise I can buy?</title>
  <createtime>2009-07-20 16:31:48</createtime>
  <nodeupdated>2009-07-20 16:31:48</nodeupdated>
</node>
