<?xml version="1.0" encoding="windows-1252"?>
<node id="492313" title="Reaped: Paths::Tree" created="2005-09-15 12:23:48" updated="2005-09-15 08:23:48">
<type id="31663">
modulereview</type>
<author id="52855">
NodeReaper</author>
<data>
<field name="doctext">
This node was taken out by the [NodeReaper] on Thu Sep 15 18:55:45 2005 GMT&lt;BR&gt;Reason:  &amp;#91;[idsfa]]: Delete: No (useful) content&lt;P&gt;For more information on this node visit:  &lt;A HREF="?nodenum=492313;node=Visit%20Reaped%20Nodes"&gt;this&lt;/A&gt;</field>
<field name="itemdescription">
Generate path from a hash tree.</field>
<field name="usercomment">
About Tree's Algorithm</field>
<field name="identifier">
</field>
</data>
</node>
