<node>
  <parent_container>19</parent_container>
  <pagetype_nodetype>871</pagetype_nodetype>
  <type_nodetype>5</type_nodetype>
  <displaytype>display</displaytype>
  <page>[{displayvars}]
[{showsitedoclet}]
[{open_new_patch_form:vars,edit}]
[%
   return $q-&gt;hidden( -name=&gt;&quot;patch_code&quot;, -value=&gt;$NODE-&gt;{vars}, -force=&gt;1 );
%]
[{closeform:Create Patch}]
&lt;br /&gt;
&lt;hr /&gt;
&lt;br /&gt;
[{listpatches}]
</page>
  <author_user>113</author_user>
  <createtime>1999-11-02 20:59:01</createtime>
  <ownedby_theme>0</ownedby_theme>
  <node_id>911</node_id>
  <title>setting display page</title>
  <mimetype></mimetype>
  <nodeupdated>2005-08-09 08:58:40</nodeupdated>
</node>
