<?xml version="1.0" encoding="windows-1252"?>
<node id="474485" title="editor_vote nuked nodes" created="2005-07-13 06:23:36" updated="2005-07-13 17:51:58">
<type id="397475">
sqlquery</type>
<author id="474174">
yitzchak</author>
<sqlqueryresult><rows_affected>614</rows_affected>
<record><editorvote_id>408979</editorvote_id>
<delvotes>4</delvotes>
</record>
<record><editorvote_id>394299</editorvote_id>
<delvotes>3</delvotes>
</record>
<record><editorvote_id>356706</editorvote_id>
<delvotes>3</delvotes>
</record>
<record><editorvote_id>353138</editorvote_id>
<delvotes>3</delvotes>
</record>
<record><editorvote_id>337652</editorvote_id>
<delvotes>3</delvotes>
</record>
<record><editorvote_id>330842</editorvote_id>
<delvotes>3</delvotes>
</record>
<record><editorvote_id>330195</editorvote_id>
<delvotes>3</delvotes>
</record>
<record><editorvote_id>329694</editorvote_id>
<delvotes>3</delvotes>
</record>
<record><editorvote_id>325934</editorvote_id>
<delvotes>3</delvotes>
</record>
<record><editorvote_id>324467</editorvote_id>
<delvotes>3</delvotes>
</record>
<record><editorvote_id>324466</editorvote_id>
<delvotes>3</delvotes>
</record>
<record><editorvote_id>313974</editorvote_id>
<delvotes>3</delvotes>
</record>
<record><editorvote_id>313881</editorvote_id>
<delvotes>3</delvotes>
</record>
<record><editorvote_id>313835</editorvote_id>
<delvotes>3</delvotes>
</record>
<record><editorvote_id>313033</editorvote_id>
<delvotes>3</delvotes>
</record>
<record><editorvote_id>311891</editorvote_id>
<delvotes>3</delvotes>
</record>
<record><editorvote_id>308614</editorvote_id>
<delvotes>3</delvotes>
</record>
<record><editorvote_id>308612</editorvote_id>
<delvotes>3</delvotes>
</record>
<record><editorvote_id>307318</editorvote_id>
<delvotes>3</delvotes>
</record>
<record><editorvote_id>305160</editorvote_id>
<delvotes>3</delvotes>
</record>
<record><editorvote_id>301821</editorvote_id>
<delvotes>3</delvotes>
</record>
<record><editorvote_id>301163</editorvote_id>
<delvotes>3</delvotes>
</record>
<record><editorvote_id>300650</editorvote_id>
<delvotes>3</delvotes>
</record>
<record><editorvote_id>297643</editorvote_id>
<delvotes>3</delvotes>
</record>
<record><editorvote_id>297641</editorvote_id>
<delvotes>3</delvotes>
</record>
<record><editorvote_id>295909</editorvote_id>
<delvotes>3</delvotes>
</record>
<record><editorvote_id>295675</editorvote_id>
<delvotes>3</delvotes>
</record>
<record><editorvote_id>295578</editorvote_id>
<delvotes>3</delvotes>
</record>
<record><editorvote_id>294046</editorvote_id>
<delvotes>3</delvotes>
</record>
<record><editorvote_id>293678</editorvote_id>
<delvotes>3</delvotes>
</record>
<record><editorvote_id>292911</editorvote_id>
<delvotes>3</delvotes>
</record>
<record><editorvote_id>290151</editorvote_id>
<delvotes>3</delvotes>
</record>
<record><editorvote_id>288753</editorvote_id>
<delvotes>3</delvotes>
</record>
<record><editorvote_id>286694</editorvote_id>
<delvotes>3</delvotes>
</record>
<record><editorvote_id>282712</editorvote_id>
<delvotes>3</delvotes>
</record>
<record><editorvote_id>281473</editorvote_id>
<delvotes>3</delvotes>
</record>
<record><editorvote_id>278846</editorvote_id>
<delvotes>3</delvotes>
</record>
<record><editorvote_id>278815</editorvote_id>
<delvotes>3</delvotes>
</record>
<record><editorvote_id>278423</editorvote_id>
<delvotes>3</delvotes>
</record>
<record><editorvote_id>277254</editorvote_id>
<delvotes>3</delvotes>
</record>
<record><editorvote_id>275183</editorvote_id>
<delvotes>3</delvotes>
</record>
<record><editorvote_id>275135</editorvote_id>
<delvotes>3</delvotes>
</record>
<record><editorvote_id>274214</editorvote_id>
<delvotes>3</delvotes>
</record>
<record><editorvote_id>271514</editorvote_id>
<delvotes>3</delvotes>
</record>
<record><editorvote_id>270825</editorvote_id>
<delvotes>3</delvotes>
</record>
<record><editorvote_id>269723</editorvote_id>
<delvotes>3</delvotes>
</record>
<record><editorvote_id>269229</editorvote_id>
<delvotes>3</delvotes>
</record>
<record><editorvote_id>268004</editorvote_id>
<delvotes>3</delvotes>
</record>
<record><editorvote_id>266932</editorvote_id>
<delvotes>3</delvotes>
</record>
<record><editorvote_id>266819</editorvote_id>
<delvotes>3</delvotes>
</record>
<record><editorvote_id>262243</editorvote_id>
<delvotes>3</delvotes>
</record>
<record><editorvote_id>261265</editorvote_id>
<delvotes>3</delvotes>
</record>
<record><editorvote_id>259620</editorvote_id>
<delvotes>3</delvotes>
</record>
<record><editorvote_id>258740</editorvote_id>
<delvotes>3</delvotes>
</record>
<record><editorvote_id>256896</editorvote_id>
<delvotes>3</delvotes>
</record>
<record><editorvote_id>254650</editorvote_id>
<delvotes>3</delvotes>
</record>
<record><editorvote_id>254227</editorvote_id>
<delvotes>3</delvotes>
</record>
<record><editorvote_id>253980</editorvote_id>
<delvotes>3</delvotes>
</record>
<record><editorvote_id>249704</editorvote_id>
<delvotes>3</delvotes>
</record>
<record><editorvote_id>248990</editorvote_id>
<delvotes>3</delvotes>
</record>
<record><editorvote_id>248342</editorvote_id>
<delvotes>3</delvotes>
</record>
<record><editorvote_id>248341</editorvote_id>
<delvotes>3</delvotes>
</record>
<record><editorvote_id>247639</editorvote_id>
<delvotes>3</delvotes>
</record>
<record><editorvote_id>236121</editorvote_id>
<delvotes>3</delvotes>
</record>
<record><editorvote_id>233301</editorvote_id>
<delvotes>3</delvotes>
</record>
<record><editorvote_id>231815</editorvote_id>
<delvotes>3</delvotes>
</record>
<record><editorvote_id>230198</editorvote_id>
<delvotes>3</delvotes>
</record>
<record><editorvote_id>229050</editorvote_id>
<delvotes>3</delvotes>
</record>
<record><editorvote_id>228387</editorvote_id>
<delvotes>3</delvotes>
</record>
<record><editorvote_id>228381</editorvote_id>
<delvotes>3</delvotes>
</record>
<record><editorvote_id>227648</editorvote_id>
<delvotes>3</delvotes>
</record>
<record><editorvote_id>224102</editorvote_id>
<delvotes>3</delvotes>
</record>
<record><editorvote_id>219974</editorvote_id>
<delvotes>3</delvotes>
</record>
<record><editorvote_id>216849</editorvote_id>
<delvotes>3</delvotes>
</record>
<record><editorvote_id>215423</editorvote_id>
<delvotes>3</delvotes>
</record>
<record><editorvote_id>215418</editorvote_id>
<delvotes>3</delvotes>
</record>
<record><editorvote_id>211358</editorvote_id>
<delvotes>3</delvotes>
</record>
<record><editorvote_id>210534</editorvote_id>
<delvotes>3</delvotes>
</record>
<record><editorvote_id>206643</editorvote_id>
<delvotes>3</delvotes>
</record>
<record><editorvote_id>203611</editorvote_id>
<delvotes>3</delvotes>
</record>
<record><editorvote_id>203126</editorvote_id>
<delvotes>3</delvotes>
</record>
<record><editorvote_id>203124</editorvote_id>
<delvotes>3</delvotes>
</record>
<record><editorvote_id>203091</editorvote_id>
<delvotes>3</delvotes>
</record>
<record><editorvote_id>196464</editorvote_id>
<delvotes>3</delvotes>
</record>
<record><editorvote_id>193352</editorvote_id>
<delvotes>3</delvotes>
</record>
<record><editorvote_id>193169</editorvote_id>
<delvotes>3</delvotes>
</record>
<record><editorvote_id>191301</editorvote_id>
<delvotes>3</delvotes>
</record>
<record><editorvote_id>189593</editorvote_id>
<delvotes>3</delvotes>
</record>
<record><editorvote_id>189592</editorvote_id>
<delvotes>3</delvotes>
</record>
<record><editorvote_id>189461</editorvote_id>
<delvotes>3</delvotes>
</record>
<record><editorvote_id>187562</editorvote_id>
<delvotes>3</delvotes>
</record>
<record><editorvote_id>187512</editorvote_id>
<delvotes>3</delvotes>
</record>
<record><editorvote_id>187349</editorvote_id>
<delvotes>3</delvotes>
</record>
<record><editorvote_id>187141</editorvote_id>
<delvotes>3</delvotes>
</record>
<record><editorvote_id>184323</editorvote_id>
<delvotes>3</delvotes>
</record>
<record><editorvote_id>183168</editorvote_id>
<delvotes>3</delvotes>
</record>
<record><editorvote_id>180396</editorvote_id>
<delvotes>3</delvotes>
</record>
<record><editorvote_id>180318</editorvote_id>
<delvotes>3</delvotes>
</record>
<record><editorvote_id>179463</editorvote_id>
<delvotes>3</delvotes>
</record>
<record><editorvote_id>177836</editorvote_id>
<delvotes>3</delvotes>
</record>
<record><editorvote_id>177256</editorvote_id>
<delvotes>3</delvotes>
</record>
<record><editorvote_id>177248</editorvote_id>
<delvotes>3</delvotes>
</record>
<record><editorvote_id>177144</editorvote_id>
<delvotes>3</delvotes>
</record>
<record><editorvote_id>176563</editorvote_id>
<delvotes>3</delvotes>
</record>
<record><editorvote_id>176006</editorvote_id>
<delvotes>3</delvotes>
</record>
<record><editorvote_id>176000</editorvote_id>
<delvotes>3</delvotes>
</record>
<record><editorvote_id>173690</editorvote_id>
<delvotes>3</delvotes>
</record>
<record><editorvote_id>172493</editorvote_id>
<delvotes>3</delvotes>
</record>
<record><editorvote_id>172116</editorvote_id>
<delvotes>3</delvotes>
</record>
<record><editorvote_id>171802</editorvote_id>
<delvotes>3</delvotes>
</record>
<record><editorvote_id>169936</editorvote_id>
<delvotes>3</delvotes>
</record>
<record><editorvote_id>169866</editorvote_id>
<delvotes>3</delvotes>
</record>
<record><editorvote_id>169477</editorvote_id>
<delvotes>3</delvotes>
</record>
<record><editorvote_id>167933</editorvote_id>
<delvotes>3</delvotes>
</record>
<record><editorvote_id>167427</editorvote_id>
<delvotes>3</delvotes>
</record>
<record><editorvote_id>167355</editorvote_id>
<delvotes>3</delvotes>
</record>
<record><editorvote_id>166946</editorvote_id>
<delvotes>3</delvotes>
</record>
<record><editorvote_id>166909</editorvote_id>
<delvotes>3</delvotes>
</record>
<record><editorvote_id>166908</editorvote_id>
<delvotes>3</delvotes>
</record>
<record><editorvote_id>166893</editorvote_id>
<delvotes>3</delvotes>
</record>
<record><editorvote_id>166773</editorvote_id>
<delvotes>3</delvotes>
</record>
<record><editorvote_id>165580</editorvote_id>
<delvotes>3</delvotes>
</record>
<record><editorvote_id>165255</editorvote_id>
<delvotes>3</delvotes>
</record>
<record><editorvote_id>164109</editorvote_id>
<delvotes>3</delvotes>
</record>
<record><editorvote_id>164001</editorvote_id>
<delvotes>3</delvotes>
</record>
<record><editorvote_id>163805</editorvote_id>
<delvotes>3</delvotes>
</record>
<record><editorvote_id>163293</editorvote_id>
<delvotes>3</delvotes>
</record>
<record><editorvote_id>162401</editorvote_id>
<delvotes>3</delvotes>
</record>
<record><editorvote_id>161127</editorvote_id>
<delvotes>3</delvotes>
</record>
<record><editorvote_id>160926</editorvote_id>
<delvotes>3</delvotes>
</record>
<record><editorvote_id>160519</editorvote_id>
<delvotes>3</delvotes>
</record>
<record><editorvote_id>160516</editorvote_id>
<delvotes>3</delvotes>
</record>
<record><editorvote_id>160494</editorvote_id>
<delvotes>3</delvotes>
</record>
<record><editorvote_id>160383</editorvote_id>
<delvotes>3</delvotes>
</record>
<record><editorvote_id>159314</editorvote_id>
<delvotes>3</delvotes>
</record>
<record><editorvote_id>158728</editorvote_id>
<delvotes>3</delvotes>
</record>
<record><editorvote_id>155782</editorvote_id>
<delvotes>3</delvotes>
</record>
<record><editorvote_id>155780</editorvote_id>
<delvotes>3</delvotes>
</record>
<record><editorvote_id>155751</editorvote_id>
<delvotes>3</delvotes>
</record>
<record><editorvote_id>155596</editorvote_id>
<delvotes>3</delvotes>
</record>
<record><editorvote_id>153772</editorvote_id>
<delvotes>3</delvotes>
</record>
<record><editorvote_id>153771</editorvote_id>
<delvotes>3</delvotes>
</record>
<record><editorvote_id>153770</editorvote_id>
<delvotes>3</delvotes>
</record>
<record><editorvote_id>153769</editorvote_id>
<delvotes>3</delvotes>
</record>
<record><editorvote_id>153768</editorvote_id>
<delvotes>3</delvotes>
</record>
<record><editorvote_id>153767</editorvote_id>
<delvotes>3</delvotes>
</record>
<record><editorvote_id>152824</editorvote_id>
<delvotes>3</delvotes>
</record>
<record><editorvote_id>151542</editorvote_id>
<delvotes>3</delvotes>
</record>
<record><editorvote_id>151300</editorvote_id>
<delvotes>3</delvotes>
</record>
<record><editorvote_id>151216</editorvote_id>
<delvotes>3</delvotes>
</record>
<record><editorvote_id>151093</editorvote_id>
<delvotes>3</delvotes>
</record>
<record><editorvote_id>150198</editorvote_id>
<delvotes>3</delvotes>
</record>
<record><editorvote_id>149877</editorvote_id>
<delvotes>3</delvotes>
</record>
<record><editorvote_id>149773</editorvote_id>
<delvotes>3</delvotes>
</record>
<record><editorvote_id>149227</editorvote_id>
<delvotes>3</delvotes>
</record>
<record><editorvote_id>149213</editorvote_id>
<delvotes>3</delvotes>
</record>
<record><editorvote_id>148750</editorvote_id>
<delvotes>3</delvotes>
</record>
<record><editorvote_id>148553</editorvote_id>
<delvotes>3</delvotes>
</record>
<record><editorvote_id>147810</editorvote_id>
<delvotes>3</delvotes>
</record>
<record><editorvote_id>147389</editorvote_id>
<delvotes>3</delvotes>
</record>
<record><editorvote_id>146973</editorvote_id>
<delvotes>3</delvotes>
</record>
<record><editorvote_id>146972</editorvote_id>
<delvotes>3</delvotes>
</record>
<record><editorvote_id>146971</editorvote_id>
<delvotes>3</delvotes>
</record>
<record><editorvote_id>146824</editorvote_id>
<delvotes>3</delvotes>
</record>
<record><editorvote_id>146783</editorvote_id>
<delvotes>3</delvotes>
</record>
<record><editorvote_id>146734</editorvote_id>
<delvotes>3</delvotes>
</record>
<record><editorvote_id>146272</editorvote_id>
<delvotes>3</delvotes>
</record>
<record><editorvote_id>146054</editorvote_id>
<delvotes>3</delvotes>
</record>
<record><editorvote_id>145971</editorvote_id>
<delvotes>3</delvotes>
</record>
<record><editorvote_id>145865</editorvote_id>
<delvotes>3</delvotes>
</record>
<record><editorvote_id>145864</editorvote_id>
<delvotes>3</delvotes>
</record>
<record><editorvote_id>145766</editorvote_id>
<delvotes>3</delvotes>
</record>
<record><editorvote_id>144439</editorvote_id>
<delvotes>3</delvotes>
</record>
<record><editorvote_id>144427</editorvote_id>
<delvotes>3</delvotes>
</record>
<record><editorvote_id>144426</editorvote_id>
<delvotes>3</delvotes>
</record>
<record><editorvote_id>144280</editorvote_id>
<delvotes>3</delvotes>
</record>
<record><editorvote_id>143345</editorvote_id>
<delvotes>3</delvotes>
</record>
<record><editorvote_id>142765</editorvote_id>
<delvotes>3</delvotes>
</record>
<record><editorvote_id>142381</editorvote_id>
<delvotes>3</delvotes>
</record>
<record><editorvote_id>138774</editorvote_id>
<delvotes>3</delvotes>
</record>
<record><editorvote_id>138773</editorvote_id>
<delvotes>3</delvotes>
</record>
<record><editorvote_id>138769</editorvote_id>
<delvotes>3</delvotes>
</record>
<record><editorvote_id>138229</editorvote_id>
<delvotes>3</delvotes>
</record>
<record><editorvote_id>138211</editorvote_id>
<delvotes>3</delvotes>
</record>
<record><editorvote_id>138208</editorvote_id>
<delvotes>3</delvotes>
</record>
<record><editorvote_id>136977</editorvote_id>
<delvotes>3</delvotes>
</record>
<record><editorvote_id>136946</editorvote_id>
<delvotes>3</delvotes>
</record>
<record><editorvote_id>136929</editorvote_id>
<delvotes>3</delvotes>
</record>
<record><editorvote_id>136765</editorvote_id>
<delvotes>3</delvotes>
</record>
<record><editorvote_id>136763</editorvote_id>
<delvotes>3</delvotes>
</record>
<record><editorvote_id>136609</editorvote_id>
<delvotes>3</delvotes>
</record>
<record><editorvote_id>136543</editorvote_id>
<delvotes>3</delvotes>
</record>
<record><editorvote_id>135767</editorvote_id>
<delvotes>3</delvotes>
</record>
<record><editorvote_id>135351</editorvote_id>
<delvotes>3</delvotes>
</record>
<record><editorvote_id>134816</editorvote_id>
<delvotes>3</delvotes>
</record>
<record><editorvote_id>134336</editorvote_id>
<delvotes>3</delvotes>
</record>
<record><editorvote_id>134226</editorvote_id>
<delvotes>3</delvotes>
</record>
<record><editorvote_id>134116</editorvote_id>
<delvotes>3</delvotes>
</record>
<record><editorvote_id>133474</editorvote_id>
<delvotes>3</delvotes>
</record>
<record><editorvote_id>133096</editorvote_id>
<delvotes>3</delvotes>
</record>
<record><editorvote_id>132980</editorvote_id>
<delvotes>3</delvotes>
</record>
<record><editorvote_id>132846</editorvote_id>
<delvotes>3</delvotes>
</record>
<record><editorvote_id>132819</editorvote_id>
<delvotes>3</delvotes>
</record>
<record><editorvote_id>132248</editorvote_id>
<delvotes>3</delvotes>
</record>
<record><editorvote_id>131636</editorvote_id>
<delvotes>3</delvotes>
</record>
<record><editorvote_id>131429</editorvote_id>
<delvotes>3</delvotes>
</record>
<record><editorvote_id>131341</editorvote_id>
<delvotes>3</delvotes>
</record>
<record><editorvote_id>131278</editorvote_id>
<delvotes>3</delvotes>
</record>
<record><editorvote_id>131017</editorvote_id>
<delvotes>3</delvotes>
</record>
<record><editorvote_id>130589</editorvote_id>
<delvotes>3</delvotes>
</record>
<record><editorvote_id>130518</editorvote_id>
<delvotes>3</delvotes>
</record>
<record><editorvote_id>130136</editorvote_id>
<delvotes>3</delvotes>
</record>
<record><editorvote_id>129979</editorvote_id>
<delvotes>3</delvotes>
</record>
<record><editorvote_id>129421</editorvote_id>
<delvotes>3</delvotes>
</record>
<record><editorvote_id>129207</editorvote_id>
<delvotes>3</delvotes>
</record>
<record><editorvote_id>128919</editorvote_id>
<delvotes>3</delvotes>
</record>
<record><editorvote_id>128408</editorvote_id>
<delvotes>3</delvotes>
</record>
<record><editorvote_id>128405</editorvote_id>
<delvotes>3</delvotes>
</record>
<record><editorvote_id>128376</editorvote_id>
<delvotes>3</delvotes>
</record>
<record><editorvote_id>128304</editorvote_id>
<delvotes>3</delvotes>
</record>
<record><editorvote_id>128282</editorvote_id>
<delvotes>3</delvotes>
</record>
<record><editorvote_id>128279</editorvote_id>
<delvotes>3</delvotes>
</record>
<record><editorvote_id>128006</editorvote_id>
<delvotes>3</delvotes>
</record>
<record><editorvote_id>127822</editorvote_id>
<delvotes>3</delvotes>
</record>
<record><editorvote_id>127791</editorvote_id>
<delvotes>3</delvotes>
</record>
<record><editorvote_id>127735</editorvote_id>
<delvotes>3</delvotes>
</record>
<record><editorvote_id>127712</editorvote_id>
<delvotes>3</delvotes>
</record>
<record><editorvote_id>127625</editorvote_id>
<delvotes>3</delvotes>
</record>
<record><editorvote_id>126882</editorvote_id>
<delvotes>3</delvotes>
</record>
<record><editorvote_id>126800</editorvote_id>
<delvotes>3</delvotes>
</record>
<record><editorvote_id>126712</editorvote_id>
<delvotes>3</delvotes>
</record>
<record><editorvote_id>126611</editorvote_id>
<delvotes>3</delvotes>
</record>
<record><editorvote_id>126327</editorvote_id>
<delvotes>3</delvotes>
</record>
<record><editorvote_id>126324</editorvote_id>
<delvotes>3</delvotes>
</record>
<record><editorvote_id>126086</editorvote_id>
<delvotes>3</delvotes>
</record>
<record><editorvote_id>125912</editorvote_id>
<delvotes>3</delvotes>
</record>
<record><editorvote_id>125906</editorvote_id>
<delvotes>3</delvotes>
</record>
<record><editorvote_id>125776</editorvote_id>
<delvotes>3</delvotes>
</record>
<record><editorvote_id>125612</editorvote_id>
<delvotes>3</delvotes>
</record>
<record><editorvote_id>125481</editorvote_id>
<delvotes>3</delvotes>
</record>
<record><editorvote_id>125250</editorvote_id>
<delvotes>3</delvotes>
</record>
<record><editorvote_id>125249</editorvote_id>
<delvotes>3</delvotes>
</record>
<record><editorvote_id>124981</editorvote_id>
<delvotes>3</delvotes>
</record>
<record><editorvote_id>124442</editorvote_id>
<delvotes>3</delvotes>
</record>
<record><editorvote_id>124432</editorvote_id>
<delvotes>3</delvotes>
</record>
<record><editorvote_id>124242</editorvote_id>
<delvotes>3</delvotes>
</record>
<record><editorvote_id>124175</editorvote_id>
<delvotes>3</delvotes>
</record>
<record><editorvote_id>124161</editorvote_id>
<delvotes>3</delvotes>
</record>
<record><editorvote_id>124147</editorvote_id>
<delvotes>3</delvotes>
</record>
<record><editorvote_id>123880</editorvote_id>
<delvotes>3</delvotes>
</record>
<record><editorvote_id>122799</editorvote_id>
<delvotes>3</delvotes>
</record>
<record><editorvote_id>122798</editorvote_id>
<delvotes>3</delvotes>
</record>
<record><editorvote_id>122797</editorvote_id>
<delvotes>3</delvotes>
</record>
<record><editorvote_id>122761</editorvote_id>
<delvotes>3</delvotes>
</record>
<record><editorvote_id>122670</editorvote_id>
<delvotes>3</delvotes>
</record>
<record><editorvote_id>122624</editorvote_id>
<delvotes>3</delvotes>
</record>
<record><editorvote_id>122328</editorvote_id>
<delvotes>3</delvotes>
</record>
<record><editorvote_id>121670</editorvote_id>
<delvotes>3</delvotes>
</record>
<record><editorvote_id>121452</editorvote_id>
<delvotes>3</delvotes>
</record>
<record><editorvote_id>120875</editorvote_id>
<delvotes>3</delvotes>
</record>
<record><editorvote_id>120872</editorvote_id>
<delvotes>3</delvotes>
</record>
<record><editorvote_id>120866</editorvote_id>
<delvotes>3</delvotes>
</record>
<record><editorvote_id>120669</editorvote_id>
<delvotes>3</delvotes>
</record>
<record><editorvote_id>120427</editorvote_id>
<delvotes>3</delvotes>
</record>
<record><editorvote_id>120426</editorvote_id>
<delvotes>3</delvotes>
</record>
<record><editorvote_id>120164</editorvote_id>
<delvotes>3</delvotes>
</record>
<record><editorvote_id>120130</editorvote_id>
<delvotes>3</delvotes>
</record>
<record><editorvote_id>120129</editorvote_id>
<delvotes>3</delvotes>
</record>
<record><editorvote_id>120121</editorvote_id>
<delvotes>3</delvotes>
</record>
<record><editorvote_id>119864</editorvote_id>
<delvotes>3</delvotes>
</record>
<record><editorvote_id>119694</editorvote_id>
<delvotes>3</delvotes>
</record>
<record><editorvote_id>119512</editorvote_id>
<delvotes>3</delvotes>
</record>
<record><editorvote_id>119449</editorvote_id>
<delvotes>3</delvotes>
</record>
<record><editorvote_id>119139</editorvote_id>
<delvotes>3</delvotes>
</record>
<record><editorvote_id>119132</editorvote_id>
<delvotes>3</delvotes>
</record>
<record><editorvote_id>119031</editorvote_id>
<delvotes>3</delvotes>
</record>
<record><editorvote_id>118915</editorvote_id>
<delvotes>3</delvotes>
</record>
<record><editorvote_id>118851</editorvote_id>
<delvotes>3</delvotes>
</record>
<record><editorvote_id>118519</editorvote_id>
<delvotes>3</delvotes>
</record>
<record><editorvote_id>118388</editorvote_id>
<delvotes>3</delvotes>
</record>
<record><editorvote_id>118334</editorvote_id>
<delvotes>3</delvotes>
</record>
<record><editorvote_id>117746</editorvote_id>
<delvotes>3</delvotes>
</record>
<record><editorvote_id>117449</editorvote_id>
<delvotes>3</delvotes>
</record>
<record><editorvote_id>116887</editorvote_id>
<delvotes>3</delvotes>
</record>
<record><editorvote_id>116539</editorvote_id>
<delvotes>3</delvotes>
</record>
<record><editorvote_id>116464</editorvote_id>
<delvotes>3</delvotes>
</record>
<record><editorvote_id>116445</editorvote_id>
<delvotes>3</delvotes>
</record>
<record><editorvote_id>116426</editorvote_id>
<delvotes>3</delvotes>
</record>
<record><editorvote_id>116425</editorvote_id>
<delvotes>3</delvotes>
</record>
<record><editorvote_id>116294</editorvote_id>
<delvotes>3</delvotes>
</record>
<record><editorvote_id>116171</editorvote_id>
<delvotes>3</delvotes>
</record>
<record><editorvote_id>115567</editorvote_id>
<delvotes>3</delvotes>
</record>
<record><editorvote_id>115566</editorvote_id>
<delvotes>3</delvotes>
</record>
<record><editorvote_id>115565</editorvote_id>
<delvotes>3</delvotes>
</record>
<record><editorvote_id>115564</editorvote_id>
<delvotes>3</delvotes>
</record>
<record><editorvote_id>115295</editorvote_id>
<delvotes>3</delvotes>
</record>
<record><editorvote_id>115288</editorvote_id>
<delvotes>3</delvotes>
</record>
<record><editorvote_id>115287</editorvote_id>
<delvotes>3</delvotes>
</record>
<record><editorvote_id>115265</editorvote_id>
<delvotes>3</delvotes>
</record>
<record><editorvote_id>115240</editorvote_id>
<delvotes>3</delvotes>
</record>
<record><editorvote_id>115044</editorvote_id>
<delvotes>3</delvotes>
</record>
<record><editorvote_id>113894</editorvote_id>
<delvotes>3</delvotes>
</record>
<record><editorvote_id>113545</editorvote_id>
<delvotes>3</delvotes>
</record>
<record><editorvote_id>113397</editorvote_id>
<delvotes>3</delvotes>
</record>
<record><editorvote_id>113337</editorvote_id>
<delvotes>3</delvotes>
</record>
<record><editorvote_id>113335</editorvote_id>
<delvotes>3</delvotes>
</record>
<record><editorvote_id>113328</editorvote_id>
<delvotes>3</delvotes>
</record>
<record><editorvote_id>113326</editorvote_id>
<delvotes>3</delvotes>
</record>
<record><editorvote_id>113325</editorvote_id>
<delvotes>3</delvotes>
</record>
<record><editorvote_id>113324</editorvote_id>
<delvotes>3</delvotes>
</record>
<record><editorvote_id>113323</editorvote_id>
<delvotes>3</delvotes>
</record>
<record><editorvote_id>113322</editorvote_id>
<delvotes>3</delvotes>
</record>
<record><editorvote_id>113320</editorvote_id>
<delvotes>3</delvotes>
</record>
<record><editorvote_id>113319</editorvote_id>
<delvotes>3</delvotes>
</record>
<record><editorvote_id>113318</editorvote_id>
<delvotes>3</delvotes>
</record>
<record><editorvote_id>113317</editorvote_id>
<delvotes>3</delvotes>
</record>
<record><editorvote_id>113316</editorvote_id>
<delvotes>3</delvotes>
</record>
<record><editorvote_id>113315</editorvote_id>
<delvotes>3</delvotes>
</record>
<record><editorvote_id>113314</editorvote_id>
<delvotes>3</delvotes>
</record>
<record><editorvote_id>113312</editorvote_id>
<delvotes>3</delvotes>
</record>
<record><editorvote_id>113311</editorvote_id>
<delvotes>3</delvotes>
</record>
<record><editorvote_id>113309</editorvote_id>
<delvotes>3</delvotes>
</record>
<record><editorvote_id>113308</editorvote_id>
<delvotes>3</delvotes>
</record>
<record><editorvote_id>113090</editorvote_id>
<delvotes>3</delvotes>
</record>
<record><editorvote_id>112715</editorvote_id>
<delvotes>3</delvotes>
</record>
<record><editorvote_id>112714</editorvote_id>
<delvotes>3</delvotes>
</record>
<record><editorvote_id>112713</editorvote_id>
<delvotes>3</delvotes>
</record>
<record><editorvote_id>112379</editorvote_id>
<delvotes>3</delvotes>
</record>
<record><editorvote_id>112368</editorvote_id>
<delvotes>3</delvotes>
</record>
<record><editorvote_id>112349</editorvote_id>
<delvotes>3</delvotes>
</record>
<record><editorvote_id>112295</editorvote_id>
<delvotes>3</delvotes>
</record>
<record><editorvote_id>112282</editorvote_id>
<delvotes>3</delvotes>
</record>
<record><editorvote_id>111810</editorvote_id>
<delvotes>3</delvotes>
</record>
<record><editorvote_id>111756</editorvote_id>
<delvotes>3</delvotes>
</record>
<record><editorvote_id>111662</editorvote_id>
<delvotes>3</delvotes>
</record>
<record><editorvote_id>111660</editorvote_id>
<delvotes>3</delvotes>
</record>
<record><editorvote_id>110798</editorvote_id>
<delvotes>3</delvotes>
</record>
<record><editorvote_id>110683</editorvote_id>
<delvotes>3</delvotes>
</record>
<record><editorvote_id>110583</editorvote_id>
<delvotes>3</delvotes>
</record>
<record><editorvote_id>110300</editorvote_id>
<delvotes>3</delvotes>
</record>
<record><editorvote_id>110183</editorvote_id>
<delvotes>3</delvotes>
</record>
<record><editorvote_id>110182</editorvote_id>
<delvotes>3</delvotes>
</record>
<record><editorvote_id>109181</editorvote_id>
<delvotes>3</delvotes>
</record>
<record><editorvote_id>109103</editorvote_id>
<delvotes>3</delvotes>
</record>
<record><editorvote_id>109098</editorvote_id>
<delvotes>3</delvotes>
</record>
<record><editorvote_id>108982</editorvote_id>
<delvotes>3</delvotes>
</record>
<record><editorvote_id>108971</editorvote_id>
<delvotes>3</delvotes>
</record>
<record><editorvote_id>108922</editorvote_id>
<delvotes>3</delvotes>
</record>
<record><editorvote_id>108612</editorvote_id>
<delvotes>3</delvotes>
</record>
<record><editorvote_id>108611</editorvote_id>
<delvotes>3</delvotes>
</record>
<record><editorvote_id>108487</editorvote_id>
<delvotes>3</delvotes>
</record>
<record><editorvote_id>108304</editorvote_id>
<delvotes>3</delvotes>
</record>
<record><editorvote_id>108283</editorvote_id>
<delvotes>3</delvotes>
</record>
<record><editorvote_id>106941</editorvote_id>
<delvotes>3</delvotes>
</record>
<record><editorvote_id>106939</editorvote_id>
<delvotes>3</delvotes>
</record>
<record><editorvote_id>106937</editorvote_id>
<delvotes>3</delvotes>
</record>
<record><editorvote_id>106936</editorvote_id>
<delvotes>3</delvotes>
</record>
<record><editorvote_id>106627</editorvote_id>
<delvotes>3</delvotes>
</record>
<record><editorvote_id>106625</editorvote_id>
<delvotes>3</delvotes>
</record>
<record><editorvote_id>106623</editorvote_id>
<delvotes>3</delvotes>
</record>
<record><editorvote_id>105947</editorvote_id>
<delvotes>3</delvotes>
</record>
<record><editorvote_id>105920</editorvote_id>
<delvotes>3</delvotes>
</record>
<record><editorvote_id>105298</editorvote_id>
<delvotes>3</delvotes>
</record>
<record><editorvote_id>104615</editorvote_id>
<delvotes>3</delvotes>
</record>
<record><editorvote_id>103740</editorvote_id>
<delvotes>3</delvotes>
</record>
<record><editorvote_id>103584</editorvote_id>
<delvotes>3</delvotes>
</record>
<record><editorvote_id>103428</editorvote_id>
<delvotes>3</delvotes>
</record>
<record><editorvote_id>102437</editorvote_id>
<delvotes>3</delvotes>
</record>
<record><editorvote_id>102433</editorvote_id>
<delvotes>3</delvotes>
</record>
<record><editorvote_id>102402</editorvote_id>
<delvotes>3</delvotes>
</record>
<record><editorvote_id>102400</editorvote_id>
<delvotes>3</delvotes>
</record>
<record><editorvote_id>102394</editorvote_id>
<delvotes>3</delvotes>
</record>
<record><editorvote_id>102196</editorvote_id>
<delvotes>3</delvotes>
</record>
<record><editorvote_id>101686</editorvote_id>
<delvotes>3</delvotes>
</record>
<record><editorvote_id>101430</editorvote_id>
<delvotes>3</delvotes>
</record>
<record><editorvote_id>101242</editorvote_id>
<delvotes>3</delvotes>
</record>
<record><editorvote_id>100865</editorvote_id>
<delvotes>3</delvotes>
</record>
<record><editorvote_id>100864</editorvote_id>
<delvotes>3</delvotes>
</record>
<record><editorvote_id>100712</editorvote_id>
<delvotes>3</delvotes>
</record>
<record><editorvote_id>100711</editorvote_id>
<delvotes>3</delvotes>
</record>
<record><editorvote_id>100596</editorvote_id>
<delvotes>3</delvotes>
</record>
<record><editorvote_id>99887</editorvote_id>
<delvotes>3</delvotes>
</record>
<record><editorvote_id>99411</editorvote_id>
<delvotes>3</delvotes>
</record>
<record><editorvote_id>99265</editorvote_id>
<delvotes>3</delvotes>
</record>
<record><editorvote_id>99229</editorvote_id>
<delvotes>3</delvotes>
</record>
<record><editorvote_id>99193</editorvote_id>
<delvotes>3</delvotes>
</record>
<record><editorvote_id>99043</editorvote_id>
<delvotes>3</delvotes>
</record>
<record><editorvote_id>98690</editorvote_id>
<delvotes>3</delvotes>
</record>
<record><editorvote_id>98616</editorvote_id>
<delvotes>3</delvotes>
</record>
<record><editorvote_id>98609</editorvote_id>
<delvotes>3</delvotes>
</record>
<record><editorvote_id>98339</editorvote_id>
<delvotes>3</delvotes>
</record>
<record><editorvote_id>98265</editorvote_id>
<delvotes>3</delvotes>
</record>
<record><editorvote_id>98226</editorvote_id>
<delvotes>3</delvotes>
</record>
<record><editorvote_id>98211</editorvote_id>
<delvotes>3</delvotes>
</record>
<record><editorvote_id>98164</editorvote_id>
<delvotes>3</delvotes>
</record>
<record><editorvote_id>97778</editorvote_id>
<delvotes>3</delvotes>
</record>
<record><editorvote_id>97758</editorvote_id>
<delvotes>3</delvotes>
</record>
<record><editorvote_id>97305</editorvote_id>
<delvotes>3</delvotes>
</record>
<record><editorvote_id>97283</editorvote_id>
<delvotes>3</delvotes>
</record>
<record><editorvote_id>97249</editorvote_id>
<delvotes>3</delvotes>
</record>
<record><editorvote_id>97248</editorvote_id>
<delvotes>3</delvotes>
</record>
<record><editorvote_id>97236</editorvote_id>
<delvotes>3</delvotes>
</record>
<record><editorvote_id>97235</editorvote_id>
<delvotes>3</delvotes>
</record>
<record><editorvote_id>97008</editorvote_id>
<delvotes>3</delvotes>
</record>
<record><editorvote_id>96715</editorvote_id>
<delvotes>3</delvotes>
</record>
<record><editorvote_id>96639</editorvote_id>
<delvotes>3</delvotes>
</record>
<record><editorvote_id>96625</editorvote_id>
<delvotes>3</delvotes>
</record>
<record><editorvote_id>95774</editorvote_id>
<delvotes>3</delvotes>
</record>
<record><editorvote_id>95769</editorvote_id>
<delvotes>3</delvotes>
</record>
<record><editorvote_id>95617</editorvote_id>
<delvotes>3</delvotes>
</record>
<record><editorvote_id>95457</editorvote_id>
<delvotes>3</delvotes>
</record>
<record><editorvote_id>95189</editorvote_id>
<delvotes>3</delvotes>
</record>
<record><editorvote_id>95160</editorvote_id>
<delvotes>3</delvotes>
</record>
<record><editorvote_id>95159</editorvote_id>
<delvotes>3</delvotes>
</record>
<record><editorvote_id>95158</editorvote_id>
<delvotes>3</delvotes>
</record>
<record><editorvote_id>95147</editorvote_id>
<delvotes>3</delvotes>
</record>
<record><editorvote_id>94964</editorvote_id>
<delvotes>3</delvotes>
</record>
<record><editorvote_id>94957</editorvote_id>
<delvotes>3</delvotes>
</record>
<record><editorvote_id>94932</editorvote_id>
<delvotes>3</delvotes>
</record>
<record><editorvote_id>94898</editorvote_id>
<delvotes>3</delvotes>
</record>
<record><editorvote_id>94862</editorvote_id>
<delvotes>3</delvotes>
</record>
<record><editorvote_id>94826</editorvote_id>
<delvotes>3</delvotes>
</record>
<record><editorvote_id>94585</editorvote_id>
<delvotes>3</delvotes>
</record>
<record><editorvote_id>94546</editorvote_id>
<delvotes>3</delvotes>
</record>
<record><editorvote_id>94520</editorvote_id>
<delvotes>3</delvotes>
</record>
<record><editorvote_id>94417</editorvote_id>
<delvotes>3</delvotes>
</record>
<record><editorvote_id>94390</editorvote_id>
<delvotes>3</delvotes>
</record>
<record><editorvote_id>94388</editorvote_id>
<delvotes>3</delvotes>
</record>
<record><editorvote_id>94386</editorvote_id>
<delvotes>3</delvotes>
</record>
<record><editorvote_id>94368</editorvote_id>
<delvotes>3</delvotes>
</record>
<record><editorvote_id>94350</editorvote_id>
<delvotes>3</delvotes>
</record>
<record><editorvote_id>94218</editorvote_id>
<delvotes>3</delvotes>
</record>
<record><editorvote_id>94207</editorvote_id>
<delvotes>3</delvotes>
</record>
<record><editorvote_id>94094</editorvote_id>
<delvotes>3</delvotes>
</record>
<record><editorvote_id>93383</editorvote_id>
<delvotes>3</delvotes>
</record>
<record><editorvote_id>93359</editorvote_id>
<delvotes>3</delvotes>
</record>
<record><editorvote_id>93344</editorvote_id>
<delvotes>3</delvotes>
</record>
<record><editorvote_id>93125</editorvote_id>
<delvotes>3</delvotes>
</record>
<record><editorvote_id>92969</editorvote_id>
<delvotes>3</delvotes>
</record>
<record><editorvote_id>92885</editorvote_id>
<delvotes>3</delvotes>
</record>
<record><editorvote_id>92870</editorvote_id>
<delvotes>3</delvotes>
</record>
<record><editorvote_id>92860</editorvote_id>
<delvotes>3</delvotes>
</record>
<record><editorvote_id>92859</editorvote_id>
<delvotes>3</delvotes>
</record>
<record><editorvote_id>92853</editorvote_id>
<delvotes>3</delvotes>
</record>
<record><editorvote_id>92850</editorvote_id>
<delvotes>3</delvotes>
</record>
<record><editorvote_id>92726</editorvote_id>
<delvotes>3</delvotes>
</record>
<record><editorvote_id>92580</editorvote_id>
<delvotes>3</delvotes>
</record>
<record><editorvote_id>92422</editorvote_id>
<delvotes>3</delvotes>
</record>
<record><editorvote_id>92380</editorvote_id>
<delvotes>3</delvotes>
</record>
<record><editorvote_id>92284</editorvote_id>
<delvotes>3</delvotes>
</record>
<record><editorvote_id>92273</editorvote_id>
<delvotes>3</delvotes>
</record>
<record><editorvote_id>92224</editorvote_id>
<delvotes>3</delvotes>
</record>
<record><editorvote_id>92144</editorvote_id>
<delvotes>3</delvotes>
</record>
<record><editorvote_id>92038</editorvote_id>
<delvotes>3</delvotes>
</record>
<record><editorvote_id>91948</editorvote_id>
<delvotes>3</delvotes>
</record>
<record><editorvote_id>91814</editorvote_id>
<delvotes>3</delvotes>
</record>
<record><editorvote_id>91775</editorvote_id>
<delvotes>3</delvotes>
</record>
<record><editorvote_id>91745</editorvote_id>
<delvotes>3</delvotes>
</record>
<record><editorvote_id>91513</editorvote_id>
<delvotes>3</delvotes>
</record>
<record><editorvote_id>91273</editorvote_id>
<delvotes>3</delvotes>
</record>
<record><editorvote_id>90981</editorvote_id>
<delvotes>3</delvotes>
</record>
<record><editorvote_id>90630</editorvote_id>
<delvotes>3</delvotes>
</record>
<record><editorvote_id>90407</editorvote_id>
<delvotes>3</delvotes>
</record>
<record><editorvote_id>90360</editorvote_id>
<delvotes>3</delvotes>
</record>
<record><editorvote_id>90340</editorvote_id>
<delvotes>3</delvotes>
</record>
<record><editorvote_id>90329</editorvote_id>
<delvotes>3</delvotes>
</record>
<record><editorvote_id>90280</editorvote_id>
<delvotes>3</delvotes>
</record>
<record><editorvote_id>90028</editorvote_id>
<delvotes>3</delvotes>
</record>
<record><editorvote_id>89992</editorvote_id>
<delvotes>3</delvotes>
</record>
<record><editorvote_id>89869</editorvote_id>
<delvotes>3</delvotes>
</record>
<record><editorvote_id>89858</editorvote_id>
<delvotes>3</delvotes>
</record>
<record><editorvote_id>89777</editorvote_id>
<delvotes>3</delvotes>
</record>
<record><editorvote_id>89677</editorvote_id>
<delvotes>3</delvotes>
</record>
<record><editorvote_id>89638</editorvote_id>
<delvotes>3</delvotes>
</record>
<record><editorvote_id>89627</editorvote_id>
<delvotes>3</delvotes>
</record>
<record><editorvote_id>89440</editorvote_id>
<delvotes>3</delvotes>
</record>
<record><editorvote_id>89268</editorvote_id>
<delvotes>3</delvotes>
</record>
<record><editorvote_id>89258</editorvote_id>
<delvotes>3</delvotes>
</record>
<record><editorvote_id>89241</editorvote_id>
<delvotes>3</delvotes>
</record>
<record><editorvote_id>89240</editorvote_id>
<delvotes>3</delvotes>
</record>
<record><editorvote_id>88876</editorvote_id>
<delvotes>3</delvotes>
</record>
<record><editorvote_id>88831</editorvote_id>
<delvotes>3</delvotes>
</record>
<record><editorvote_id>88748</editorvote_id>
<delvotes>3</delvotes>
</record>
<record><editorvote_id>87874</editorvote_id>
<delvotes>3</delvotes>
</record>
<record><editorvote_id>87506</editorvote_id>
<delvotes>3</delvotes>
</record>
<record><editorvote_id>87446</editorvote_id>
<delvotes>3</delvotes>
</record>
<record><editorvote_id>87402</editorvote_id>
<delvotes>3</delvotes>
</record>
<record><editorvote_id>87371</editorvote_id>
<delvotes>3</delvotes>
</record>
<record><editorvote_id>87370</editorvote_id>
<delvotes>3</delvotes>
</record>
<record><editorvote_id>87369</editorvote_id>
<delvotes>3</delvotes>
</record>
<record><editorvote_id>87368</editorvote_id>
<delvotes>3</delvotes>
</record>
<record><editorvote_id>87326</editorvote_id>
<delvotes>3</delvotes>
</record>
<record><editorvote_id>87306</editorvote_id>
<delvotes>3</delvotes>
</record>
<record><editorvote_id>87290</editorvote_id>
<delvotes>3</delvotes>
</record>
<record><editorvote_id>87289</editorvote_id>
<delvotes>3</delvotes>
</record>
<record><editorvote_id>85084</editorvote_id>
<delvotes>3</delvotes>
</record>
<record><editorvote_id>84988</editorvote_id>
<delvotes>3</delvotes>
</record>
<record><editorvote_id>84987</editorvote_id>
<delvotes>3</delvotes>
</record>
<record><editorvote_id>84751</editorvote_id>
<delvotes>3</delvotes>
</record>
<record><editorvote_id>84575</editorvote_id>
<delvotes>3</delvotes>
</record>
<record><editorvote_id>83943</editorvote_id>
<delvotes>3</delvotes>
</record>
<record><editorvote_id>83886</editorvote_id>
<delvotes>3</delvotes>
</record>
<record><editorvote_id>83859</editorvote_id>
<delvotes>3</delvotes>
</record>
<record><editorvote_id>83858</editorvote_id>
<delvotes>3</delvotes>
</record>
<record><editorvote_id>83432</editorvote_id>
<delvotes>3</delvotes>
</record>
<record><editorvote_id>83320</editorvote_id>
<delvotes>3</delvotes>
</record>
<record><editorvote_id>83067</editorvote_id>
<delvotes>3</delvotes>
</record>
<record><editorvote_id>83058</editorvote_id>
<delvotes>3</delvotes>
</record>
<record><editorvote_id>82785</editorvote_id>
<delvotes>3</delvotes>
</record>
<record><editorvote_id>82570</editorvote_id>
<delvotes>3</delvotes>
</record>
<record><editorvote_id>82267</editorvote_id>
<delvotes>3</delvotes>
</record>
<record><editorvote_id>82266</editorvote_id>
<delvotes>3</delvotes>
</record>
<record><editorvote_id>82265</editorvote_id>
<delvotes>3</delvotes>
</record>
<record><editorvote_id>82203</editorvote_id>
<delvotes>3</delvotes>
</record>
<record><editorvote_id>82030</editorvote_id>
<delvotes>3</delvotes>
</record>
<record><editorvote_id>82029</editorvote_id>
<delvotes>3</delvotes>
</record>
<record><editorvote_id>82027</editorvote_id>
<delvotes>3</delvotes>
</record>
<record><editorvote_id>82025</editorvote_id>
<delvotes>3</delvotes>
</record>
<record><editorvote_id>82024</editorvote_id>
<delvotes>3</delvotes>
</record>
<record><editorvote_id>82023</editorvote_id>
<delvotes>3</delvotes>
</record>
<record><editorvote_id>81865</editorvote_id>
<delvotes>3</delvotes>
</record>
<record><editorvote_id>81393</editorvote_id>
<delvotes>3</delvotes>
</record>
<record><editorvote_id>81352</editorvote_id>
<delvotes>3</delvotes>
</record>
<record><editorvote_id>81066</editorvote_id>
<delvotes>3</delvotes>
</record>
<record><editorvote_id>80993</editorvote_id>
<delvotes>3</delvotes>
</record>
<record><editorvote_id>80782</editorvote_id>
<delvotes>3</delvotes>
</record>
<record><editorvote_id>80756</editorvote_id>
<delvotes>3</delvotes>
</record>
<record><editorvote_id>80532</editorvote_id>
<delvotes>3</delvotes>
</record>
<record><editorvote_id>80524</editorvote_id>
<delvotes>3</delvotes>
</record>
<record><editorvote_id>80511</editorvote_id>
<delvotes>3</delvotes>
</record>
<record><editorvote_id>79512</editorvote_id>
<delvotes>3</delvotes>
</record>
<record><editorvote_id>79381</editorvote_id>
<delvotes>3</delvotes>
</record>
<record><editorvote_id>78945</editorvote_id>
<delvotes>3</delvotes>
</record>
<record><editorvote_id>78841</editorvote_id>
<delvotes>3</delvotes>
</record>
<record><editorvote_id>78420</editorvote_id>
<delvotes>3</delvotes>
</record>
<record><editorvote_id>78324</editorvote_id>
<delvotes>3</delvotes>
</record>
<record><editorvote_id>77592</editorvote_id>
<delvotes>3</delvotes>
</record>
<record><editorvote_id>77590</editorvote_id>
<delvotes>3</delvotes>
</record>
<record><editorvote_id>77466</editorvote_id>
<delvotes>3</delvotes>
</record>
<record><editorvote_id>77328</editorvote_id>
<delvotes>3</delvotes>
</record>
<record><editorvote_id>77127</editorvote_id>
<delvotes>3</delvotes>
</record>
<record><editorvote_id>76457</editorvote_id>
<delvotes>3</delvotes>
</record>
<record><editorvote_id>75796</editorvote_id>
<delvotes>3</delvotes>
</record>
<record><editorvote_id>75154</editorvote_id>
<delvotes>3</delvotes>
</record>
<record><editorvote_id>74029</editorvote_id>
<delvotes>3</delvotes>
</record>
<record><editorvote_id>73366</editorvote_id>
<delvotes>3</delvotes>
</record>
<record><editorvote_id>73090</editorvote_id>
<delvotes>3</delvotes>
</record>
<record><editorvote_id>72752</editorvote_id>
<delvotes>3</delvotes>
</record>
<record><editorvote_id>72404</editorvote_id>
<delvotes>3</delvotes>
</record>
<record><editorvote_id>72307</editorvote_id>
<delvotes>3</delvotes>
</record>
<record><editorvote_id>71204</editorvote_id>
<delvotes>3</delvotes>
</record>
<record><editorvote_id>70773</editorvote_id>
<delvotes>3</delvotes>
</record>
<record><editorvote_id>70615</editorvote_id>
<delvotes>3</delvotes>
</record>
<record><editorvote_id>70055</editorvote_id>
<delvotes>3</delvotes>
</record>
<record><editorvote_id>70054</editorvote_id>
<delvotes>3</delvotes>
</record>
<record><editorvote_id>69014</editorvote_id>
<delvotes>3</delvotes>
</record>
<record><editorvote_id>67810</editorvote_id>
<delvotes>3</delvotes>
</record>
<record><editorvote_id>67113</editorvote_id>
<delvotes>3</delvotes>
</record>
<record><editorvote_id>67023</editorvote_id>
<delvotes>3</delvotes>
</record>
<record><editorvote_id>66525</editorvote_id>
<delvotes>3</delvotes>
</record>
<record><editorvote_id>65991</editorvote_id>
<delvotes>3</delvotes>
</record>
<record><editorvote_id>63553</editorvote_id>
<delvotes>3</delvotes>
</record>
<record><editorvote_id>63210</editorvote_id>
<delvotes>3</delvotes>
</record>
<record><editorvote_id>63033</editorvote_id>
<delvotes>3</delvotes>
</record>
<record><editorvote_id>62836</editorvote_id>
<delvotes>3</delvotes>
</record>
<record><editorvote_id>62761</editorvote_id>
<delvotes>3</delvotes>
</record>
<record><editorvote_id>62133</editorvote_id>
<delvotes>3</delvotes>
</record>
<record><editorvote_id>61138</editorvote_id>
<delvotes>3</delvotes>
</record>
<record><editorvote_id>59566</editorvote_id>
<delvotes>3</delvotes>
</record>
<record><editorvote_id>59422</editorvote_id>
<delvotes>3</delvotes>
</record>
<record><editorvote_id>58885</editorvote_id>
<delvotes>3</delvotes>
</record>
<record><editorvote_id>57946</editorvote_id>
<delvotes>3</delvotes>
</record>
<record><editorvote_id>57429</editorvote_id>
<delvotes>3</delvotes>
</record>
<record><editorvote_id>54844</editorvote_id>
<delvotes>3</delvotes>
</record>
<record><editorvote_id>54843</editorvote_id>
<delvotes>3</delvotes>
</record>
<record><editorvote_id>54529</editorvote_id>
<delvotes>3</delvotes>
</record>
<record><editorvote_id>53550</editorvote_id>
<delvotes>3</delvotes>
</record>
<record><editorvote_id>53517</editorvote_id>
<delvotes>3</delvotes>
</record>
<record><editorvote_id>52077</editorvote_id>
<delvotes>3</delvotes>
</record>
<record><editorvote_id>45698</editorvote_id>
<delvotes>3</delvotes>
</record>
<record><editorvote_id>44945</editorvote_id>
<delvotes>3</delvotes>
</record>
<record><editorvote_id>43945</editorvote_id>
<delvotes>3</delvotes>
</record>
<record><editorvote_id>41741</editorvote_id>
<delvotes>3</delvotes>
</record>
<record><editorvote_id>40563</editorvote_id>
<delvotes>3</delvotes>
</record>
<record><editorvote_id>39794</editorvote_id>
<delvotes>3</delvotes>
</record>
<record><editorvote_id>39793</editorvote_id>
<delvotes>3</delvotes>
</record>
<record><editorvote_id>39636</editorvote_id>
<delvotes>3</delvotes>
</record>
<record><editorvote_id>37941</editorvote_id>
<delvotes>3</delvotes>
</record>
<record><editorvote_id>35547</editorvote_id>
<delvotes>3</delvotes>
</record>
<record><editorvote_id>35302</editorvote_id>
<delvotes>3</delvotes>
</record>
<record><editorvote_id>34899</editorvote_id>
<delvotes>3</delvotes>
</record>
<record><editorvote_id>34836</editorvote_id>
<delvotes>3</delvotes>
</record>
<record><editorvote_id>33085</editorvote_id>
<delvotes>3</delvotes>
</record>
<record><editorvote_id>32260</editorvote_id>
<delvotes>3</delvotes>
</record>
<record><editorvote_id>32259</editorvote_id>
<delvotes>3</delvotes>
</record>
<record><editorvote_id>31984</editorvote_id>
<delvotes>3</delvotes>
</record>
<record><editorvote_id>31813</editorvote_id>
<delvotes>3</delvotes>
</record>
<record><editorvote_id>28658</editorvote_id>
<delvotes>3</delvotes>
</record>
<record><editorvote_id>26967</editorvote_id>
<delvotes>3</delvotes>
</record>
<record><editorvote_id>26965</editorvote_id>
<delvotes>3</delvotes>
</record>
<record><editorvote_id>26414</editorvote_id>
<delvotes>3</delvotes>
</record>
<record><editorvote_id>24390</editorvote_id>
<delvotes>3</delvotes>
</record>
<record><editorvote_id>24085</editorvote_id>
<delvotes>3</delvotes>
</record>
<record><editorvote_id>19155</editorvote_id>
<delvotes>3</delvotes>
</record>
<record><editorvote_id>18457</editorvote_id>
<delvotes>3</delvotes>
</record>
<record><editorvote_id>15994</editorvote_id>
<delvotes>3</delvotes>
</record>
<record><editorvote_id>11704</editorvote_id>
<delvotes>3</delvotes>
</record>
<record><editorvote_id>5215</editorvote_id>
<delvotes>3</delvotes>
</record>
<record><editorvote_id>5050</editorvote_id>
<delvotes>3</delvotes>
</record>
<record><editorvote_id>4993</editorvote_id>
<delvotes>3</delvotes>
</record>
<record><editorvote_id>4553</editorvote_id>
<delvotes>3</delvotes>
</record>
<record><editorvote_id>4552</editorvote_id>
<delvotes>3</delvotes>
</record>
<record><editorvote_id>3368</editorvote_id>
<delvotes>3</delvotes>
</record>
<record><editorvote_id>1708</editorvote_id>
<delvotes>3</delvotes>
</record>
</sqlqueryresult>
</node>
