<?xml version="1.0" encoding="windows-1252"?>
<node id="523122" title="Zombies That shouldn't be." created="2006-01-13 20:21:01" updated="2006-01-13 15:21:01">
<type id="397475">
sqlquery</type>
<author id="357600">
de-merphq</author>
<sqlqueryresult><rows_affected>5</rows_affected>
<record><title>Zombie sravan2001</title>
<author_user>108170</author_user>
<num>2</num>
</record>
<record><title>Zombie lrenigu</title>
<author_user>113948</author_user>
<num>2</num>
</record>
<record><title>Zombie dubx56</title>
<author_user>116533</author_user>
<num>2</num>
</record>
<record><title>Zombie perlmonks</title>
<author_user>173939</author_user>
<num>2</num>
</record>
<record><title>Zombie codehopper</title>
<author_user>241047</author_user>
<num>2</num>
</record>
</sqlqueryresult>
</node>
