<?xml version="1.0" encoding="windows-1252"?>
<node id="640853" title="Reaped:" created="2007-09-24 22:48:54" updated="2007-09-24 18:48:54">
<type id="31670">
bookreview</type>
<author id="52855">
NodeReaper</author>
<data>
<field name="doctext">
This node was taken out by the [NodeReaper] on [localtime://2007-09-25 00-27-05]&lt;BR&gt;Reason:  &amp;#91;[atcroft]]: reap: no content/empty posting&lt;p&gt;You may view [href://?node=Visit%20Reaped%20Nodes&amp;nodenum=640853|the original node and the consideration vote tally].&lt;/p&gt;</field>
<field name="itemdescription">
</field>
<field name="usercomment">
</field>
<field name="identifier">
</field>
</data>
</node>
